{"forum": {"content": "1 \u865f\u51fa\u53e3 \uff06 2 \u865f\u51fa\u53e3", "images": ["http://filestoresg1.beetalkmobile.com:8081/file/a1f3150c60c0a3b23372ee050fb059ae"], "urls": [], "title": "\u25cf.\u25cf \u9078  \u64c7"}, "threadStatus": 0, "regionId": 886, "barStatus": 0, "barId": 10, "postBy": {"utc": 1496203186000, "level": 25, "location": "\u53f0\u4e2d\u5e02\u00b7\u53f0\u7063", "avatar": "http://filestoresg1.beetalkmobile.com:8081/file/-5739484760241883541", "name": "\u4e00\u8449\u5b50\u4e00 \ud83c\udf43"}, "id": 6010628}
