{"forum": {"content": "\u59b3\u5011\u9858\u610f\u82b1\u591a\u4e45\u6642\u9593<br />\u7b49\u4e00\u500b\u958b\u82b1\u7d50\u679c\uff1f", "images": ["http://filestoresg1.beetalkmobile.com:8081/file/9eb3e3d9f2074f335a16b130ae102eb7"], "urls": [], "title": "\u6709\u4e9b\u4eba\u8d70\u904e\u8def\u904e\u4e0d\u662f\u70ba\u4e86\u505c\u7559"}, "threadStatus": 0, "regionId": 886, "barStatus": 0, "barId": 13, "postBy": {"utc": 1509860421000, "level": 3, "location": "\u53f0\u5357\u5e02\u00b7\u53f0\u7063", "avatar": "http://filestoresg1.beetalkmobile.com:8081/file/9041551320051083940", "name": "\u898f"}, "id": 6964091}
