{"forum": {"content": "\u7d04650\uff0c710\u624d\u8d77\u5e8a\uff0c\u628a\u5ee0\u5546\u653e\u9ce5\u6211\u4e5f\u662f\u4f69\u670d\u6211\u81ea\u5df1\u7684......", "images": ["http://filestoresg1.beetalkmobile.com:8081/file/ad9d91f06b485da1869db7c1b26290c1", "http://filestoresg1.beetalkmobile.com:8081/file/2f855f0384badc14735dfbe09a969860", "http://filestoresg1.beetalkmobile.com:8081/file/46430db098604e88f2e2a4164f642e6c", "http://filestoresg1.beetalkmobile.com:8081/file/4c179e24e0f267ef5d701cb44ab296f7"], "urls": [], "title": "\u65b0\u52a0\u5761\u690d\u7269\u516c\u5712\u4e4b\u9072\u5230\u8d74\u7d04..."}, "threadStatus": 0, "regionId": 886, "barStatus": 0, "barId": 85, "postBy": {"utc": 1502842370000, "level": 4, "location": "Singapore\u00b7\u65b0\u52a0\u5761", "avatar": "http://filestoresg1.beetalkmobile.com:8081/file/-4759392193447566592", "name": "Tool Man"}, "id": 6454403}
