{"forum": {"content": "\u653e\u4e86\u611b\u60c5\u4e00\u6bb5\u5047\u671f\uff0c\u662f\u8a72\u6536\u5047\u4e86...<br /><br />\u770b\u9019\u8eab\u65c1\u7684\u670b\u53cb\uff0c\u4e00\u500b\u500b\u7684\u544a\u5225\u55ae\u8eab\uff0c<br /><br />\u6211\u662f\u8a72\u52aa\u529b\u627e\u500b\u4e56\u5de7\u7684\u5973\u5b69\uff0c\u544a\u5225\u55ae\u8eab\uff0c<br /><br />PS:\u64c7\u5076\u689d\u4ef6~\u4e56\u5de7\uff0c\u4f11\u5047\u6642\u80fd\u5920\u966a\u6211\uff0c<br /><br />\u770b\u770b\u96fb\u5f71\uff0c\u5403\u5403\u7f8e\u98df\uff0c\u8e0f\u8e0f\u9752\uff0c\u901b\u901b\u8857\uff0c<br /><br />\u966a\u4f34\u5c31\u662f\u6700\u5e78\u798f\u7684\u4e8b\u3002<br />                        <br />                        \u59b3\u4e0d\u7528\u591a\u597d\uff0c\u6211\u559c\u6b61\u5c31\u597d\u3002<br /><br />\u55ef\uff0c\u4e0d\u77e5\u9053\u8981\u8aaa\u4ec0\u9ebc\u4e86\uff0c\u54c8\u54c8\u54c8\u2026<br /><br />\u6c92\u932f\u5c31\u662f\u59b3\uff0c\u8d95\u5feb\u4f86\u8a8d\u8b58\uff0c\u8a8d\u8b58^.^~<br /><br />\u653e\u5fc3\uff0c\u804a\u51fa\u611f\u60c5\u6211\u6703\u8ca0\u8cac\uff0c\u563b\u563b^\u00b7^~<br /><br />\u671f\u5f85\u5c08\u5c6c\u6211\u7684\u59b3\uff0c\u5feb\u5feb\u51fa\u73fe\uff01\uff01<br />", "images": ["http://filestoresg1.beetalkmobile.com:8081/file/aaf14a52e463d92cc4871ea95c8c0c28", "http://filestoresg1.beetalkmobile.com:8081/file/8061cd8d7ab9e8c771f9308eb226ef88"], "urls": [], "title": "\u55ae\u8eab\u4e00\u679a\uff01\uff01\u5fb5\u5973\u53cb\uff01\uff01"}, "threadStatus": 0, "regionId": 886, "barStatus": 0, "barId": 205, "postBy": {"utc": 1498056108000, "level": 3, "location": "\u5f70\u5316\u7e23\u00b7\u53f0\u7063", "avatar": "http://filestoresg1.beetalkmobile.com:8081/file/5132043105664784713", "name": "\u7121\u79c1\u4e5d"}, "id": 6135083}
