{"forum": {"content": "\u6211\u662f\u5927\u53d4\uff0c\u6211\u4e0d\u5e25\uff0c\u6211\u4e0d\u7626<br />\u4f46\u6211\u53ea\u60f3\u7d14\u4ea4\u4ea4\u670b\u53cb\uff0c\u804a\u804a\u5929\uff01<br />\u9858\u610f\u7684\u2026\u6b61\u8fce\u5149\u81e8<br />\u4e0d\u9858\u610f\u7684\u2026\u8b1d\u8b1d\u6536\u770b", "images": ["http://filestoresg1.beetalkmobile.com:8081/file/8ed8a9d99092ed5893226de45741ac2b"], "urls": [], "title": "\u4ea4\u670b\u53cb\u3001\u804a\u804a\u5929\u3001\u5206\u4eab\u751f\u6d3b\u53ca\u559c\u597d"}, "threadStatus": 0, "regionId": 886, "barStatus": 0, "barId": 838, "postBy": {"utc": 1507867235000, "level": 2, "location": "\u9ad8\u96c4\u5e02\u00b7\u53f0\u7063", "avatar": "http://filestoresg1.beetalkmobile.com:8081/file/-6941391712967707392", "name": "\u7279\u52d9 KAN"}, "id": 6815161}
