{"forum": {"content": "\u8eab\u6750?<br />\u6a23\u8c8c?<br />\u9738\u6c23?<br />\u65af\u6587?<br />\u9084\u662f????", "images": ["http://filestoresg1.beetalkmobile.com:8081/file/7a61446ab0dbe40f9272e49894e3dd3f"], "urls": [], "title": "\u5973\u751f\u9078\u64c7\u7537\u4eba....\u7684\u689d\u4ef6\u70ba\u4f55?"}, "threadStatus": 0, "regionId": 886, "barStatus": 2, "barId": 732, "postBy": {"utc": 1502566235000, "level": 3, "location": "\u65b0\u7af9\u5e02\u00b7\u53f0\u7063", "avatar": "http://filestoresg1.beetalkmobile.com:8081/file/3081793676820558097", "name": "\u60f3\u8eab\u5bf8"}, "id": 6435418}
