{"forum": {"content": "\u7ba1\u4f60\u662f\u8ab0\u90fd\u4f86\u627e\u6211\u804a\ud83d\ude08", "images": ["http://filestoresg1.beetalkmobile.com:8081/file/218bd0e7ad6a23b1cb17802b5a052823"], "urls": [], "title": "\u9664\u4e86\u7121\u804a\u9084\u662f\u7121\u804a"}, "threadStatus": 0, "regionId": 886, "barStatus": 0, "barId": 20, "postBy": {"utc": 1508602777000, "level": 4, "location": "\u53f0\u5317\u5e02\u00b7\u53f0\u7063", "avatar": "http://filestoresg1.beetalkmobile.com:8081/file/-4607555134425965031", "name": "yu\ud83c\udf38"}, "id": 6876014}
