{"forum": {"content": "\u55ae\u9ede\u5305 \u9580+\u79681000<br /><br />\u540d\u984d\u5269\u4e09\u4f4d \u6709\u8208\u8da3\u7684\u670b\u53cb\u5feb\u4f86\u627e\u6211\u5594", "images": ["http://filestoresg1.beetalkmobile.com:8081/file/cc132a5299d9a22a752021d875f28974"], "urls": [], "title": "11/3 wave \u63ea\u5718\u611b\u96fb\u97f3\u8db4\u7684\u670b\u53cb"}, "threadStatus": 0, "regionId": 886, "barStatus": 0, "barId": 792, "postBy": {"utc": 1509459009000, "level": 2, "location": "\u65b0\u5317\u5e02\u00b7\u53f0\u7063", "avatar": "http://filestoresg1.beetalkmobile.com:8081/file/5150183933957420544", "name": "\u264a\u66fe\u5c0f\u5929"}, "id": 6933198}
