{"forum": {"content": "\u676d\u5dde\u6cb3\u574a\u8857", "images": ["http://filestoresg1.beetalkmobile.com:8081/file/36e5ddc338fe817a85cd290cc2b13b47", "http://filestoresg1.beetalkmobile.com:8081/file/dca20bff8a21dc463c6040fd8b87daf6", "http://filestoresg1.beetalkmobile.com:8081/file/3925cf3a465c8470203ed3a99ae047c2", "http://filestoresg1.beetalkmobile.com:8081/file/5c869a5e4c8505fc5173162008c779ac", "http://filestoresg1.beetalkmobile.com:8081/file/9b39e4928d69128b84235f9ebb4809f1"], "urls": [], "title": "\u4e2d\u56ef\u884c"}, "threadStatus": 0, "regionId": 886, "barStatus": 0, "barId": 85, "postBy": {"utc": 1502981311000, "level": 12, "location": "\u9ad8\u96c4\u5e02\u00b7\u53f0\u7063", "avatar": "http://filestoresg1.beetalkmobile.com:8081/file/4538346398631156172", "name": "\ud64d\ube48(\u0e1e\u0e38\u0e12)"}, "id": 6464338}
