{"forum": {"content": "\u5f9e\u4f86\u90fd\u6c92\u6709\u4e00\u500b\u77e5\u5fc3\u7684\u4eba\u966a\u8457\u6211\ud83e\udd37\u200d\u2640\ufe0f<br />\u53ea\u6709\u6211\u7684\u5c0f\u80d6\u5b50<br /><br />\u6bcf\u6b21\u90fd\u88ab\u6234\u7da0\u5e3d\u53ea\u80fd\u8aaa \u50bb\u773c<br /><br />\u9019\u88e1\u4e0d\u662f\u59d0\u5f1f\u6200\u55ce\uff1f\u59d0\u59d0\u5728\u54ea\u88e1<br />\u5feb\u4f86\u627e\u6211\u804a\u5929\ud83d\ude22\u2b55\ufe0f", "images": ["http://filestoresg1.beetalkmobile.com:8081/file/9f75be1454722e2cc88acfc3b121a270", "http://filestoresg1.beetalkmobile.com:8081/file/484f1e75e98a58eb09727580b80a647b"], "urls": [], "title": " \u5b64\u7368\u842c\u6b72 \u5931\u6200\u7121\u7f6a"}, "threadStatus": 1, "regionId": 886, "barStatus": 0, "barId": 734, "postBy": {"utc": 1510023779000, "level": 1, "location": "\u53f0\u5317\u5e02\u00b7\u53f0\u7063", "avatar": "http://filestoresg1.beetalkmobile.com:8081/file/6407451306188525571", "name": "Daniel Lin\ud83d\ude0e 180\ud83e\udd2b"}, "id": 6977698}
