{"forum": {"content": "\u6211\u9700\u8981\u6b63\u80fd\u91cf\ud83e\udd26\ud83c\udffc\u200d\u2640\ufe0f", "images": ["http://filestoresg1.beetalkmobile.com:8081/file/b7ffffb3f4a1cbf1fd3df241ca9e1bd0"], "urls": [], "title": "\u966a\u6211\u804a\u804a"}, "threadStatus": 0, "regionId": 886, "barStatus": 0, "barId": 20, "postBy": {"utc": 1509551902000, "level": 1, "location": "\u65b0\u5317\u5e02\u00b7\u53f0\u7063", "avatar": "http://filestoresg1.beetalkmobile.com:8081/file/-4524915835571041279", "name": "\u5321\u6613"}, "id": 6940917}
