{"forum": {"content": "\u5973\u751f\u4e00\u767c\u6587\uff0c\u5e7e\u767e\u4eba\u6309\u8b9a\u7559\u8a00<br />\u7537\u751f\u4e00\u767c\u6587\uff0c\u767c\u6587\u8005\u4e00\u4eba\u6309\u8b9a", "images": ["http://filestoresg1.beetalkmobile.com:8081/file/b260d6a26006a0fe25f60ec8b90d8fa9"], "urls": [], "title": "\u770b\u90fd\u89ba\u5f97\u602a\u7684\u73fe\u8c61"}, "threadStatus": 0, "regionId": 886, "barStatus": 0, "barId": 205, "postBy": {"utc": 1508847565000, "level": 2, "location": "Taipei City\u00b7Taiwan", "avatar": "http://filestoresg1.beetalkmobile.com:8081/file/1221322123855353602", "name": "Peter Yu"}, "id": 6896515}
