{"forum": {"content": "\u53ef\u4ee5\u4f86\u804a\u5929\u8a8d\u8b58\u4e00\u4e0b\u55ce", "images": ["http://filestoresg1.beetalkmobile.com:8081/file/261b9ee0f9ed120e70290ae8435c36cf"], "urls": [], "title": "\u59b3\u5011\u597d"}, "threadStatus": 0, "regionId": 886, "barStatus": 0, "barId": 734, "postBy": {"utc": 1500457429000, "level": 1, "location": "\u65b0\u5317\u5e02\u00b7\u53f0\u7063", "avatar": "http://filestoresg1.beetalkmobile.com:8081/file/-4994131345765364992", "name": "Kkk"}, "id": 6292496}
