{"forum": {"content": "\u597d\u840c\u597d\u840c", "images": ["http://filestoresg1.beetalkmobile.com:8081/file/88db0e78ca680c4ae3729c24730f389c"], "urls": [], "title": "\u9019\u500b\u2026"}, "threadStatus": 0, "regionId": 886, "barStatus": 0, "barId": 422, "postBy": {"utc": 1498467590000, "level": 20, "location": "\u53f0\u5317\u5e02\u00b7\u53f0\u7063", "avatar": "http://filestoresg1.beetalkmobile.com:8081/file/-3787729589472358778", "name": "\u53ea\u5269\u6253\u5361\u529f\u80fd@\u6587 \ud83d\ude48\ud83d\ude49\ud83d\ude4a"}, "id": 6160397}
