{"forum": {"content": "\u4e0d\u6311  \u53ea\u8981\u6709\u5fc3\u5c31\u597d \ud83d\udc9a", "images": ["http://filestoresg1.beetalkmobile.com:8081/file/a46f9fbeb62265aebdfd0626689d9b42", "http://filestoresg1.beetalkmobile.com:8081/file/ff374a2e54e5ba1d881cee70083c8e2c"], "urls": [], "title": "\u627e\u500b\u4f34"}, "threadStatus": 1, "regionId": 886, "barStatus": 0, "barId": 20, "postBy": {"utc": 1503934286000, "level": 1, "location": "\u53f0\u7063", "avatar": "http://filestoresg1.beetalkmobile.com:8081/file/-2389415766038137112", "name": "\u5c0f\u6afb\u6843"}, "id": 6531687}
