{"forum": {"content": "\u597d\u50cf\u5728\u5065\u8eab\u7684\u6642\u4faf<br />\u8e29\u8e29\u98db\u8f2a<br />\u4e0a\u4e0aBC<br /><br /><br />\u7684\u6642\u5019<br /><br /><br />\u6709\u4e9b\u5973\u751f\u7279\u5225\u597d\u52dd<br /><br /><br /><br />\u96e3\u9053\u6211\u6709\u9019\u7a2e\u529f\u80fd<br /><br /><br />\u3002\u3002\u3002\u3002<br /><br /><br /><br /><br /><br /><br /><br /><br />\u5973\u751f\u5230\u5e95\u770b\u5230\u4e86\u6211\u4ec0\u9ebc\uff1f\uff1f<br /><br /><br /><br />\u6211\u77e5\u9053\u6211\u904b\u52d5\u91cf\u5df2\u662f<br /><br /><br />\u4f46<br /><br /><br />\u7e3d\u89ba\u5f97<br /><br /><br />\u6709\u9ed8\u9ed8\u4e00\u7968\u5973\u751f<br /><br /><br />\u5728<br /><br />\u6709\u6c27\u8ab2\u7a0b<br /><br />\u6e96\u5099\u8d85\u8d8a\u6211\u7684\u611f\u89ba<br /><br /><br /><br /><br />\u4e00\u9032\u6559\u5ba4\u5c31\u88ab<br /><br />\u4e00\u76f4\u7576\u52d5\u7269\u770b<br /><br /><br />\u3002\u3002\u3002\u3002\u3002<br /><br /><br /><br /><br /><br /><br /><br /><br />", "images": ["http://filestoresg1.beetalkmobile.com:8081/file/5c7161d380ed09d9adb59b287bc392a7"], "urls": [], "title": "\u7e3d\u89ba\u5f97"}, "threadStatus": 1, "regionId": 886, "barStatus": 0, "barId": 707, "postBy": {"utc": 1498844392000, "level": 1, "location": "New Taipei City\u00b7Taiwan", "avatar": "http://filestoresg1.beetalkmobile.com:8081/file/5022480070185297285", "name": "\u65b0\u5317\u5df4\u85a9\u62c9"}, "id": 6185191}
