{"forum": {"content": "** \u82f1\u96c4\u806f\u76df  **<br /><br />\u6b61\u8fce\u8a8d\u8b58\u7576\u500b\u670b\u53cb\u5427<br />\u73a9\u7684\u958b\u5fc3\u5c31\u597d\u5427okay<br />\u597d\u53cb\u53ef\u4ee5\u52a0\u54e6///<br /><br />ID:  Bettermeet<br /><br /><br /><br />", "images": ["http://filestoresg1.beetalkmobile.com:8081/file/9f24d3b9df5bff8b27968d432c649ea4"], "urls": [], "title": "\u4f60 / \u59b3 \u4e00\u8d77\u73a9\u5427 \u597d\u53cb \u968a\u53cb  \u2795 \u2795"}, "threadStatus": 1, "regionId": 886, "barStatus": 0, "barId": 60, "postBy": {"utc": 1502799999000, "level": 1, "location": "\u53f0\u7063", "avatar": "http://filestoresg1.beetalkmobile.com:8081/file/5558938378468752820", "name": "\ud83d\udc36"}, "id": 6451676}
