{"forum": {"content": "\u6700\u8fd1\u5728\u7db2\u4e0a\u5f88\u7d05\u7684app\uff0c\u5927\u5bb6\u6709\u7528\u904e\u55ce\uff1f\ud83d\ude02\ud83d\ude02<br />\u2191\u2191\u6c92\u932f~\u9019\u5c31\u662f\u6211\ud83d\ude4b", "images": ["http://filestoresg1.beetalkmobile.com:8081/file/f3471d4eaa9a8f7ef1964098256b61ae", "http://filestoresg1.beetalkmobile.com:8081/file/854500dc9ea82a2a7996d8b68e16dfde", "http://filestoresg1.beetalkmobile.com:8081/file/bcaf2bfe47de5879643c832e6b111425"], "urls": [], "title": "\u4eac\u5287\u611b\u597d\u8005\ud83d\udc83\ud83d\udc83"}, "threadStatus": 0, "regionId": 886, "barStatus": 0, "barId": 35, "postBy": {"utc": 1503492269000, "level": 1, "location": "\u53f0\u5317\u5e02\u00b7\u53f0\u7063", "avatar": "http://filestoresg1.beetalkmobile.com:8081/file/-4221524294049689095", "name": "Bowen Chen"}, "id": 6500048}
