{"forum": {"content": "\u90a3\u4e9b\u4e0d\u6109\u5feb\uff0c\u96a8\u8457\u9ec3\u6e6f\u4e0b\u809a", "images": ["http://filestoresg1.beetalkmobile.com:8081/file/4bd2927dd1db0dc099fdafdfe399024b"], "urls": [], "title": "\u5fc3\u4e8b\u5ba3\u6d29"}, "threadStatus": 0, "regionId": 886, "barStatus": 0, "barId": 792, "postBy": {"utc": 1500751547000, "level": 1, "location": "Pingtung County\u00b7Taiwan", "avatar": "http://filestoresg1.beetalkmobile.com:8081/file/-1445490544533534482", "name": "BOB"}, "id": 6313044}
