{"forum": {"content": "\u9019\u5e74\u6062\u5fa9\u55ae\u8eab \u751f\u65e5\u5c11\u4e86\u3002\u3002\u67d0\u7a2e\u6771\u897f<br /><br /><br />\u5144\u5f1f\u611f\u8b1d\u4f60\u8acb\u5ba2", "images": ["http://filestoresg1.beetalkmobile.com:8081/file/e782b1e4e24893ca9bb785b27c8a82d4"], "urls": [], "title": "\u751f\u65e5\u7d50\u675f\u4e86"}, "threadStatus": 1, "regionId": 886, "barStatus": 0, "barId": 205, "postBy": {"utc": 1499788668000, "level": 2, "location": "\u53f0\u4e2d\u5e02\u00b7\u53f0\u7063", "avatar": "http://filestoresg1.beetalkmobile.com:8081/file/-2434711246664968189", "name": "\u66ab\u505c\u4f7f\u7528"}, "id": 6247890}
