{"forum": {"content": "\u6700\u8fd1\u771f\u7684\u7121\u804a\u5230\u767c\u614c <br />\u627e\u804a\u5929\u6216\u662f\u559d\u9152\u4f34", "images": ["http://filestoresg1.beetalkmobile.com:8081/file/7dc645ed70eafaf640f65222a2a5ec76", "http://filestoresg1.beetalkmobile.com:8081/file/bddbc17b741c65733f9b845efdeab443", "http://filestoresg1.beetalkmobile.com:8081/file/3597fcd927cac10b9a48523ae7280a35"], "urls": [], "title": "\u6211\u5011\u4f86\u804a\u5929\uff5e\uff5e\uff5e\uff5e"}, "threadStatus": 0, "regionId": 886, "barStatus": 0, "barId": 20, "postBy": {"utc": 1499785110000, "level": 2, "location": "\u53f0\u5317\u5e02\u00b7\u53f0\u7063", "avatar": "http://filestoresg1.beetalkmobile.com:8081/file/5300613617024161536", "name": "\u897f\u897f\u6b6a"}, "id": 6247489}
