{"forum": {"content": "\u559c\u6b61\u804a\u5929\u7684\u4eba\u4ea4\u500b\u670b\u53cb\u5427<3", "images": ["http://filestoresg1.beetalkmobile.com:8081/file/5020779ffb0dae13f25a59921d6fcfce"], "urls": [], "title": "\u65b0\u624b\u4e0a\u8def"}, "threadStatus": 1, "regionId": 886, "barStatus": 0, "barId": 422, "postBy": {"utc": 1504716626000, "level": 2, "location": "\u53f0\u5357\u5e02\u00b7\u53f0\u7063", "avatar": "http://filestoresg1.beetalkmobile.com:8081/file/-7582023256197076221", "name": "\u6708 \u6708"}, "id": 6583878}
