{"forum": {"content": "\u624b\u6a5f\u62cd\u651d~", "images": ["http://filestoresg1.beetalkmobile.com:8081/file/150306ecbfd81533271b5ad293c0e1e7", "http://filestoresg1.beetalkmobile.com:8081/file/c48491dcfd6de6d7c5b7bc93643dd250", "http://filestoresg1.beetalkmobile.com:8081/file/076071cc51a718d43ed732c504627991", "http://filestoresg1.beetalkmobile.com:8081/file/6b78de6de61d6b363147d45f7fbbdd4b", "http://filestoresg1.beetalkmobile.com:8081/file/021a4793bd08c74e736f51e45286db10"], "urls": [], "title": "8/29\u971e\u5149~\uff08\u624b\u6a5f\u62cd\u651d\uff09"}, "threadStatus": 0, "regionId": 886, "barStatus": 0, "barId": 77, "postBy": {"utc": 1504062394000, "level": 17, "location": "", "avatar": "http://filestoresg1.beetalkmobile.com:8081/file/6433167780409076092", "name": "\u6cf0\u8fea"}, "id": 6539432}
