{"forum": {"content": "\u597d\u50cf\u5f88\u5c11\u4eba\u5728\u72c4\u6069\u5929\u795e\ud83e\udd14<br />\u4e00\u6a23\u7684\u53ef\u4ee5\u52a0\u597d\u53cb\u4e00\u8d77\u7d44\u968a\u639b\u6838\u5fc3\ud83d\ude04\ud83d\ude04", "images": ["http://filestoresg1.beetalkmobile.com:8081/file/e659c471a04c31bd0a53e9f7e37a69fe"], "urls": [], "title": "\uff08\u66f4\uff09\u5929\u5802\u4e8c\uff5e\u6709\u4eba\u8981\u4e00\u8d77\u73a9\u55ce"}, "threadStatus": 0, "regionId": 886, "barStatus": 0, "barId": 59, "postBy": {"utc": 1498631948000, "level": 2, "location": "\u65b0\u5317\u5e02\u00b7\u53f0\u7063", "avatar": "http://filestoresg1.beetalkmobile.com:8081/file/2319776021968679696", "name": "\ud83c\udf38\u7fa4\u7fa4\ud83c\udf38"}, "id": 6170876}
