{"forum": {"content": "\u54c8\u56c9 \u5927\u5bb6 \u8a8d\u8b58\u4e00\u4e0b\u5427\ud83d\ude42", "images": ["http://filestoresg1.beetalkmobile.com:8081/file/76a360964b166d8fbdbfa79a47002835", "http://filestoresg1.beetalkmobile.com:8081/file/8f655c47f886baba584c88363066b2b5", "http://filestoresg1.beetalkmobile.com:8081/file/26d28b1839554d57107c3918d309ffa6", "http://filestoresg1.beetalkmobile.com:8081/file/67febe6f5842904543bda6d165fe92de"], "urls": [], "title": "\u8a8d\u8b58\ud83c\udf38"}, "threadStatus": 1, "regionId": 886, "barStatus": 0, "barId": 4, "postBy": {"utc": 1496239887000, "level": 3, "location": "\u82b1\u84ee\u7e23\u00b7\u53f0\u7063", "avatar": "http://filestoresg1.beetalkmobile.com:8081/file/-5828338512549147611", "name": "\u6f58\ud83d\udd25"}, "id": 6013405}
