{"forum": {"content": "\u662f\u4e0d\u662f\u592a\u611b\u54ed \u6240\u4ee5\u773c\u775b\u624d\u9019\u9ebc\u5c0f", "images": ["http://filestoresg1.beetalkmobile.com:8081/file/524984a9df2bbebfb23e98acda496a72"], "urls": [], "title": "\u807d\u8aaa\u8d8a\u611b\u54ed\u7684\u4eba\u8d8a\u5805\u5f37\ud83d\ude45\ud83d\udeb1"}, "threadStatus": 0, "regionId": 886, "barStatus": 0, "barId": 205, "postBy": {"utc": 1496238169000, "level": 3, "location": "\u65b0\u7af9\u5e02\u00b7\u53f0\u7063", "avatar": "http://filestoresg1.beetalkmobile.com:8081/file/-1920673072890324669", "name": "IG\uff1aa_mao870514"}, "id": 6013212}
