{"forum": {"content": "\u7db2\u8def\u4e0a\u770b\u8655\u5973\u8ddf\u91d1\u725b\u6700\u914d\uff0c<br />\u70ba\u4ec0\u9ebc\u6211\u89ba\u5f97\u91d1\u725b\u500b\u6027\u813e\u6c23\u90fd\u4e0d\u597d\uff0c<br />\u53ea\u6709\u505a\u611b\u4ed6\u624d\u6703\u5f88\u4e56\u5f88\u914d\u5408\u2026\u2026\u83ab\u540d\u5947\u5999\uff01", "images": ["http://filestoresg1.beetalkmobile.com:8081/file/5cf6d476b458dd1059006e57eef02c8a"], "urls": [], "title": "\u661f\u5ea7\u914d\u5c0d\u7591\u554f"}, "threadStatus": 0, "regionId": 886, "barStatus": 0, "barId": 205, "postBy": {"utc": 1503885451000, "level": 9, "location": "\u9ad8\u96c4\u5e02\u00b7\u53f0\u7063", "avatar": "http://filestoresg1.beetalkmobile.com:8081/file/5137519762975572251", "name": "\u62ff\u9435 \u3001"}, "id": 6527425}
