{"forum": {"content": "\u6709\u4e00\u6b21\u8ddf\u524d\u7537\u53cb\u5435\u67b6\u5435\u5f97\u975e\u5e38\u5147<br />\u4ed6\u5c31\u4e00\u76f4\u5435\u8457\u8aaa\u8ddf\u6211\u76f8\u8655\u4e0d\u5feb\u6a02..<br />\u65bc\u662f\u6211\u5c31\u8cb7\u4e86\u4e00\u7f50\u808c\u6a02\u56de\u4f86\u5674\u4ed6..<br />\u70ba\u4f55\u4ed6\u5c31\u628a\u6211\u8d95\u51fa\u53bb\u4e86o(\u00b4\uff65_\uff65`)o", "images": ["http://filestoresg1.beetalkmobile.com:8081/file/3ee3afe073769e297c80adbaf68d9392"], "urls": [], "title": "\u7537\u751f\u5f88\u96e3\u6e9d\u901a\ud83d\ude14"}, "threadStatus": 0, "regionId": 886, "barStatus": 0, "barId": 205, "postBy": {"utc": 1496653807000, "level": 8, "location": "\u53f0\u5317\u5e02\u00b7\u53f0\u7063", "avatar": "http://filestoresg1.beetalkmobile.com:8081/file/3126142461619185690", "name": "\u82bd\u82bd\ud83c\udf77"}, "id": 6041385}
