{"forum": {"content": "\u5c0f\u805a\u4e00\u4e0b\u6c92\u95dc\u4fc2\u5427", "images": ["http://filestoresg1.beetalkmobile.com:8081/file/6f06f234f9ab349546503ab224d04857"], "urls": [], "title": "\u4e0b\u96e8\u5929\u662f\u500b\u559d\u9152\u5929"}, "threadStatus": 0, "regionId": 886, "barStatus": 0, "barId": 727, "postBy": {"utc": 1496639973000, "level": 23, "location": "\u53f0\u5357\u5e02\u00b7\u53f0\u7063", "avatar": "http://filestoresg1.beetalkmobile.com:8081/file/-8676447462794638411", "name": "\u5e03\u8c37\u6069"}, "id": 6040401}
