{"forum": {"content": " \u5982\u679c\u59b3\u9858\u610f<br />\u3002<br />\u3002<br />\u3002<br />\u3002<br />\u3002<br />\u3002<br />\u3002<br />\u3002<br />\u3002<br />\u3002<br />\u3002<br />\u3002<br />\u3002<br />\u3002<br />\u3002<br />\u3002<br />\u3002<br />\u3002<br />\u3002<br />\u3002<br />\u3002<br />\u80fd\u5426\u8b93\u6211\u8a8d\u8b58\u59b3\ud83e\udd17", "images": ["http://filestoresg1.beetalkmobile.com:8081/file/ce3c3a0cdfd9ff8c634c6180118f6138"], "urls": [], "title": "\u78ba\u5b9a\u4e0d\u8ffd\ud83d\ude44"}, "threadStatus": 1, "regionId": 886, "barStatus": 0, "barId": 20, "postBy": {"utc": 1510077971000, "level": 7, "location": "\u6843\u5712\u5e02\u00b7\u53f0\u7063", "avatar": "http://filestoresg1.beetalkmobile.com:8081/file/-1173297631531333803", "name": "wenfl"}, "id": 6983160}
