{"forum": {"content": "\u60f3\u627e\u4e00\u4f4d \u6210\u719f\u800c\u53c8\u4e0d\u7169\u7684\u59d0\u59d0<br />\u53ea\u8981\u5927\u65bc20\u6b72\u5c31\u53ef\u4ee5\u4e86", "images": ["http://filestoresg1.beetalkmobile.com:8081/file/d6cd918196012d7b13c0a4aa54f680d3"], "urls": [], "title": "\u6211\u7684\u59d0\u59d0\u4f60\u5728\u54ea\u88e1"}, "threadStatus": 1, "regionId": 886, "barStatus": 0, "barId": 734, "postBy": {"utc": 1505263493000, "level": 1, "location": "\u53f0\u4e2d\u5e02\u00b7\u53f0\u7063", "avatar": "http://filestoresg1.beetalkmobile.com:8081/file/-4045227500490850607", "name": "\u8f1d\u4ed4"}, "id": 6620137}
