{"forum": {"content": "\u5f88\u4e45\u6c92\u63d0\u7b46\u5275\u4f5c\u5c0f\u8aaa\u4e86\uff0c<br />\u5e7e\u4e4e\u5fd8\u4e86\u521d\u521d\u7684\u90a3\u4efd\u71b1\u8840\u8207\u611f\u52d5\u3002<br /><br />\u4e5f\u8a31\uff0c\u662f\u6211\u7684\u5fc3\uff0c\u5805\u97cc\u4e0d\u5920\uff0c<br />\u4e5f\u8a31\uff0c\u662f\u6211\u7684\u8a5e\u85fb\uff0c\u592a\u904e\u65bc\u8584\u5f31\uff0c<br />\u4eba\u7684\u85c9\u53e3\uff0c\u4e00\u65e6\u592a\u591a\uff0c<br />\u9748\u9b42\uff0c\u4fbf\u5bb9\u6613\u8ddf\u8457\u6c89\u6dea\u9677\u843d\u3002<br /><br />\u91ce\u751c\u83ca\u662f\u4ec0\u9ebc\uff1f<br />\u6211\u5f9e\u4f86\u4e0d\u61c2\uff01<br />\u5373\u4f7f\u66fe\u7d93\u5728\u773c\u524d\u7dbb\u653e\u8457\uff0c<br />\u6211\u4e5f\u65e9\u5df2\u932f\u904e...\u3002<br /><br />\u9a40\u7136\u56de\u7738\uff0c<br />\u4eba\u751f\u884c\u5982\u8def\u908a\u52aa\u529b\u7ac4\u51fa\u77f3\u7e2b\u7684\u5c0f\u5c0f\u91ce\u82b1\u4e00\u6735\uff0c<br />\u5728\u98a8\u4e2d\uff0c\u5b64\u7368\u5730\uff0c\u50bb\u50bb\u7b11\u8457...<br /><br />(\u5716\u8f49\u81ea\u7db2\u8def)", "images": ["http://filestoresg1.beetalkmobile.com:8081/file/3ed7d352800be20f8d2d8b475fd42376"], "urls": [], "title": "\u80e1\u601d"}, "threadStatus": 1, "regionId": 886, "barStatus": 0, "barId": 707, "postBy": {"utc": 1507287131000, "level": 6, "location": "\u53f0\u5317\u5e02\u00b7\u53f0\u7063", "avatar": "http://filestoresg1.beetalkmobile.com:8081/file/-6267051348045453612", "name": "\u6b64\u5e33\u865f\u5df2\u522a\u9664"}, "id": 6767941}
