{"forum": {"content": "\u5617\u8a66\u770b\u51fa\u7a7a\u9593\u7684\u7bc0\u594f\uff0c\u8a66\u8457\u8b80\u51fa\u57ce\u5e02\u7684\u6545\u4e8b\u3002", "images": ["http://filestoresg1.beetalkmobile.com:8081/file/9c82a76ad4a6fce217890d1806d419ee", "http://filestoresg1.beetalkmobile.com:8081/file/9462998987fd4dcdb08ea5c330a2015d", "http://filestoresg1.beetalkmobile.com:8081/file/ed1bc515f60b3169900b5e15132c560a", "http://filestoresg1.beetalkmobile.com:8081/file/0b1c390495a2ccaed8678e6bbc38f345"], "urls": [], "title": "\u7df4\u7fd2\uff0c\u57ce\u5e02"}, "threadStatus": 0, "regionId": 886, "barStatus": 0, "barId": 77, "postBy": {"utc": 1496296012000, "level": 1, "location": "", "avatar": "http://filestoresg1.beetalkmobile.com:8081/file/-7357071972560846587", "name": "\u4e94\u6708\u98a8\u7b8f"}, "id": 6016894}
