{"forum": {"content": "\u611f\u89ba\u65b0\u7684\u8ff7\u5f69\u670d\u6709\u9ede......=.=\"", "images": ["http://filestoresg1.beetalkmobile.com:8081/file/4acf2f6bcfc79bbafa0267a735c8c8a9", "http://filestoresg1.beetalkmobile.com:8081/file/209dd19959c8bebcde79e6679e38b3a4", "http://filestoresg1.beetalkmobile.com:8081/file/1287cbb36334977e1f26eebf98c32d91"], "urls": [], "title": "\u5ff5\u820a\u672a\u5fc5\u662f\u58de\u4e8b~\u9084\u662f\u820a\u7684\u597d...(*\u02d8\ufe36\u02d8*)"}, "threadStatus": 0, "regionId": 886, "barStatus": 0, "barId": 391, "postBy": {"utc": 1506408678000, "level": 16, "location": "\u65b0\u5317\u5e02\u00b7\u53f0\u7063", "avatar": "http://filestoresg1.beetalkmobile.com:8081/file/4694017462545750353", "name": "\u671b\u661f~\u671b\u6708~\u671b\u591c\u7a7a!!"}, "id": 6699574}
