{"forum": {"content": "\u804a\u5929\u8a8d\u8b58\u4e00\u4e0b \u5ea6\u904e\u7121\u804a\u7684\u79ae\u62dc\u65e5\ud83d\ude02<br />\u5c4f\u6771\u6392\u7063\u4f4f\u53f0\u4e2d", "images": ["http://filestoresg1.beetalkmobile.com:8081/file/5404088f214d9f96b71775b561b7c079"], "urls": [], "title": "\u65e9\u5b89"}, "threadStatus": 1, "regionId": 886, "barStatus": 0, "barId": 727, "postBy": {"utc": 1504417442000, "level": 2, "location": "\u53f0\u4e2d\u5e02\u00b7\u53f0\u7063", "avatar": "http://filestoresg1.beetalkmobile.com:8081/file/8066834244131298306", "name": "\u77ee\u5b50\u502b"}, "id": 6562914}
