{"forum": {"content": "\u6211\u6709\u6545\u4e8b\u4f60\u6709\u9152\u55ce\uff1f", "images": ["http://filestoresg1.beetalkmobile.com:8081/file/8a26360fb242537c634b5999170cdb34"], "urls": [], "title": "\u60f3\u627e\u59d0\u8ac7\u8ac7\u5fc3\u3002\u621122\u6b72\u3002\u6b61\u8fce\u505a\u670b\u53cb"}, "threadStatus": 0, "regionId": 886, "barStatus": 0, "barId": 734, "postBy": {"utc": 1504409094000, "level": 3, "location": "\u6843\u5712\u5e02\u00b7\u53f0\u7063", "avatar": "http://filestoresg1.beetalkmobile.com:8081/file/6964563951391263234", "name": "\u715c\u51f1"}, "id": 6562254}
