{"forum": {"content": "\u6700\u8fd1\u771f\u7684\u5f88\u760b\u9019\u500b\u54c8\u54c8\u54c8<br />\u4ec0\u9ebc\u6709\u81c9\u7684\u90fd\u8981\u62ff\u4f86\u8a66\u8a66\u770bXD<br />\u53ef\u662f\u73ed\u4e0a\u90fd\u6c92\u4eba\u8981\u8ddf\u6211\u4e00\u8d77\u73a9<br />\u5230\u5e95\u662f\u6211\u592a\u908a\u7de3\u9084\u662f\u5927\u5bb6\u90fd\u4e0d\u559c\u6b61snow\ud83d\ude10<br />(\u53ef..\u53ef\u60e1\u6c92\u8fa6\u6cd5\u653e\u5f71\u7247\u554a\u554a\u554a\u554a\u554a\uff01", "images": ["http://filestoresg1.beetalkmobile.com:8081/file/6f2d1b66a482a65f811dd9222acf3486", "http://filestoresg1.beetalkmobile.com:8081/file/bb56b9036c0684ac918b670c1e834785", "http://filestoresg1.beetalkmobile.com:8081/file/f2f322f3c4c8fcdc0471f2a97f2565db", "http://filestoresg1.beetalkmobile.com:8081/file/2af060f4eb07be73013a9b8ff0550cd1", "http://filestoresg1.beetalkmobile.com:8081/file/cdd56cc383cc598d9d338bc04f488243", "http://filestoresg1.beetalkmobile.com:8081/file/90154b3a052b76edd60130c18acf1a3d"], "urls": [], "title": "\u6709\u4eba\u4e5f\u5728\u73a9snow\u55ce\ud83d\ude02"}, "threadStatus": 1, "regionId": 886, "barStatus": 0, "barId": 438, "postBy": {"utc": 1503925115000, "level": 3, "location": "\u53f0\u7063", "avatar": "http://filestoresg1.beetalkmobile.com:8081/file/6537778612013158768", "name": "\ud83d\udc19"}, "id": 6530661}
