{"forum": {"content": "\u77e5\u9053\u70ba\u4ec0\u9ebcNi\u7684\u901a\u8a0a\u8edf\u9ad4\u8a0a\u606f\u90a3\u9ebc\u5c11\u55ce\uff1f<br />\u56e0\u70baNi\u66fe\u7d93\u70ba\u4e86\u4e00\u500b\u4eba\u9060\u96e2\u6240\u6709\u4eba<br />\u4e00\u7121\u6240\u6709<br />\u4f46Ni\u4ecd\u7136\u5fd8\u4e0d\u4e86Ta<br />\u7562\u7adf\u5fc3\u88e1\u90fd\u662fTa<br /><br />\u5fd8\u4e86\uff0c\u5fc3\u5c31\u7a7a\u4e86", "images": ["http://filestoresg1.beetalkmobile.com:8081/file/8545bff9efa6c9beae6bc580cb141b1e"], "urls": [], "title": "\u91cd\u5fc3"}, "threadStatus": 0, "regionId": 886, "barStatus": 0, "barId": 707, "postBy": {"utc": 1509820310000, "level": 3, "location": "\u53f0\u7063", "avatar": "http://filestoresg1.beetalkmobile.com:8081/file/-3433549411576977471", "name": "."}, "id": 6961746}
