{"forum": {"content": "\u3127\u6a23\u7684\u5230\u8655\u9a19\u7167\u7247", "images": ["http://filestoresg1.beetalkmobile.com:8081/file/a8378aa8b7bafc9782f6845c42af71fa", "http://filestoresg1.beetalkmobile.com:8081/file/063e4fffd9970b055946fc660444671c", "http://filestoresg1.beetalkmobile.com:8081/file/0a42ba1ed16711b23b9e46646d88f551", "http://filestoresg1.beetalkmobile.com:8081/file/801ff74ddd9f4b805458a27772f7fbc8", "http://filestoresg1.beetalkmobile.com:8081/file/b9d57538e2c3e7c5296cc9a8dd59c2ad", "http://filestoresg1.beetalkmobile.com:8081/file/0e2f5b20cf92f59ac7ab0aa2e5dc6473"], "urls": [], "title": "\u8ffd\u98a8\u8001\u4eba"}, "threadStatus": 0, "regionId": 886, "barStatus": 0, "barId": 838, "postBy": {"utc": 1508731282000, "level": 8, "location": "\u5f70\u5316\u7e23\u00b7\u53f0\u7063", "avatar": "http://filestoresg1.beetalkmobile.com:8081/file/-2943270580857310616", "name": "\u87f9\u963f\u91d1"}, "id": 6886369}
