{"forum": {"content": "\u4e0d\u5b9a\u671f\u8209\u8fa6\u5a5a\u7d17\u62cd\u651d\u8a08\u5283<br /><br />\u6709\u8208\u8da3\u7684\u53ef\u4ee5\u52a0\u597d\u53cb<br /><br />\u5e74\u9f6118-22\u6709\u52a0\u5206 \u8b1d\u8b1d", "images": ["http://filestoresg1.beetalkmobile.com:8081/file/b6c86f8f22346d2c466dc8656ab9e2df"], "urls": [], "title": "\u53f0\u5317\u79ae\u670d\u5de5\u4f5c\u5ba4"}, "threadStatus": 0, "regionId": 886, "barStatus": 0, "barId": 77, "postBy": {"utc": 1506477726000, "level": 1, "location": "\u53f0\u5317\u5e02\u00b7\u53f0\u7063", "avatar": "http://filestoresg1.beetalkmobile.com:8081/file/-3031046787073050188", "name": "stanley"}, "id": 6704619}
