{"forum": {"content": "-.-", "images": ["http://filestoresg1.beetalkmobile.com:8081/file/19f63b224b87bfe9b30d2b6790995d42", "http://filestoresg1.beetalkmobile.com:8081/file/f7a48ca7a613b6a50c2ac13e2dff7929", "http://filestoresg1.beetalkmobile.com:8081/file/f5fe28da629338023ede8a4e286962c2"], "urls": [], "title": "\u73fe\u5728\u73fe\u5728\u8ab0\u8981\u4e00\u8d77\u6392\uff5e\u6b61\u6a02\u70ba\u4e3b\uff01\u9280\u56db\uff01\u6700\u9ad8\u91d1\u4e00"}, "threadStatus": 0, "regionId": 886, "barStatus": 0, "barId": 60, "postBy": {"utc": 1502198761000, "level": 10, "location": "\u53f0\u5357\u5e02\u00b7\u53f0\u7063", "avatar": "http://filestoresg1.beetalkmobile.com:8081/file/-7684227280550424701", "name": "\u9999\u8549\u4f60\u500b\u62d4\u6a02"}, "id": 6410917}
