{"forum": {"content": "\u88ab\u525d\u596a\u767c\u8a00\u6b0a\u4e86\u5462<br /><br />\u4e0d\u80fd\u767c\u5ee2\u6587\u73a9\u9019\u500b\u5e79\u561b\u5566\uff0c\u91cd\u65b0\u5b89\u88dd\u4e5f\u6c92\u7528<br /><br />\u4e0d\u9084\u7d66\u6211\u4e3b\u9801\u662f\u8981\u6211\u5728\u5404\u500b\u7248\u767c\u5ee2\u6587\u64fe\u6c11\u55ce\uff1f<br /><br />\u96d6\u7136\u5927\u5bb6\u90fd\u7121\u8996\u6240\u4ee5\u6c92\u5dee(\u25cd\u2022\u1d17\u2022\u25cd) <br /><br /><br />\u5c0d\u4e86<br /><br />\u6211\u53ea\u662f\u60f3\u554f\u4f60\u5011\u5348\u9910\u8981\u5403\u4ec0\u9ebc\u800c\u5df2", "images": ["http://filestoresg1.beetalkmobile.com:8081/file/29d8227aeb879273c728aca7f623791d", "http://filestoresg1.beetalkmobile.com:8081/file/a776bb8e2f27f83e65d9a587e4c04112", "http://filestoresg1.beetalkmobile.com:8081/file/529951ba452a441f682041e70c0c0d9b", "http://filestoresg1.beetalkmobile.com:8081/file/ba9f9c670c97f4bd4b5a31f58f148524"], "urls": [], "title": "\u7981\u8a00"}, "threadStatus": 1, "regionId": 886, "barStatus": 0, "barId": 391, "postBy": {"utc": 1497406794000, "level": 10, "location": "\u4fc4\u7f85\u65af", "avatar": "http://filestoresg1.beetalkmobile.com:8081/file/-7544275937043260299", "name": "\u8d85\u4eba\u6c23\u5154\u51542.0"}, "id": 6092180}
