{"forum": {"content": "\u6709\u5e25\u54e5\u59b9\u5b50\u8981\u8a8d\u8b58\u55ce", "images": ["http://filestoresg1.beetalkmobile.com:8081/file/fe883c23e7e61b5f961c646fc5c53e16"], "urls": [], "title": "\u4f86\u8a8d\u8b58"}, "threadStatus": 0, "regionId": 886, "barStatus": 0, "barId": 32, "postBy": {"utc": 1510215128000, "level": 1, "location": "\u53f0\u5317\u5e02\u00b7\u53f0\u7063", "avatar": "http://filestoresg1.beetalkmobile.com:8081/file/5005048404661888003", "name": "\u7f8b\u7f8b\ud83d\udc8b"}, "id": 6993746}
