{"forum": {"content": "\u6709\u89e3\u7b54\u55ce:)", "images": ["http://filestoresg1.beetalkmobile.com:8081/file/79cabfa505f19ae44114d6acf5f09d01", "http://filestoresg1.beetalkmobile.com:8081/file/0535223c8a2e587de113aca64b69503b"], "urls": [], "title": "\u91d1\u982d\u8166"}, "threadStatus": 1, "regionId": 886, "barStatus": 0, "barId": 752, "postBy": {"utc": 1507014214000, "level": 3, "location": "\u9ad8\u96c4\u5e02\u00b7\u53f0\u7063", "avatar": "http://filestoresg1.beetalkmobile.com:8081/file/7057657407593428681", "name": "\u857e\u857e"}, "id": 6746178}
