{"forum": {"content": "\u611f\u89ba\u4ed6\u7761\u5f88\u751c  \u5728\u60f3\u660e\u5929\u7684 \u6f54\u7259\u9aa8 \ud83d\ude02\ud83d\ude02", "images": ["http://filestoresg1.beetalkmobile.com:8081/file/a3e9ca5446b6f4e9208fcf9803e6a3c1", "http://filestoresg1.beetalkmobile.com:8081/file/67db40d7c06805603e8f42386dbedb63", "http://filestoresg1.beetalkmobile.com:8081/file/3c60771bf90135529317dd8e7f056f96", "http://filestoresg1.beetalkmobile.com:8081/file/67da7d83e5f3f6dc8921f082ef8821d8"], "urls": [], "title": "\u7761\u7684\u5f88\u9999\u7684\u72d7"}, "threadStatus": 1, "regionId": 886, "barStatus": 0, "barId": 105, "postBy": {"utc": 1507014437000, "level": 2, "location": "\u53f0\u7063", "avatar": "http://filestoresg1.beetalkmobile.com:8081/file/3963284223528456477", "name": "\u6c92\u6709\u7d55\u5c0d \u5c0d\u8207\u932f"}, "id": 6746202}
