{"forum": {"content": "\u55ae\u8eab\u4e45\u4e86\u6703\u7fd2\u6163\u7684\u2764\ufe0f", "images": ["http://filestoresg1.beetalkmobile.com:8081/file/7fa35011f5e570c5e908f68e91e89d35"], "urls": [], "title": "\u2764\ufe0f"}, "threadStatus": 0, "regionId": 886, "barStatus": 0, "barId": 205, "postBy": {"utc": 1503759167000, "level": 2, "location": "\u6843\u5712\u5e02\u00b7\u53f0\u7063", "avatar": "http://filestoresg1.beetalkmobile.com:8081/file/7260356756098037761", "name": "#\ud83d\udd0dFB\ud83c\udf80\u5b89\u6c99\u66c9\ud83c\udf80"}, "id": 6518785}
