{"forum": {"content": "\u6642\u9593\u665a\u4e0a12\uff1a30\uff5e6\u9ede<br />\u56e0\u70ba\u6700\u8fd1\u4e0a\u5927\u591c  \u724c\u4f4d\u5927\u6982\u91d1\u5de6\u53f3   \u4e0d\u96f7\u7684  \u7559\u4e0bid\u516b", "images": ["http://filestoresg1.beetalkmobile.com:8081/file/cae1ceb818b3d062c320ffa38659c5d0"], "urls": [], "title": "\u627e\u722c\u5206"}, "threadStatus": 0, "regionId": 886, "barStatus": 0, "barId": 60, "postBy": {"utc": 1508968515000, "level": 3, "location": "\u6843\u5712\u5e02\u00b7\u53f0\u7063", "avatar": "http://filestoresg1.beetalkmobile.com:8081/file/9184182165618175571", "name": "\u54a9\u54a9"}, "id": 6901714}
