{"forum": {"content": "\u4e58\u53d7\u8457<br />\u5b64\u5bc2<br />\u6c88\u9ed8<br />\u53eb\u7f75<br />\u5931\u843d<br />\u9019\u9846\u5fc3\u9084\u8981\u591a\u4e45<br />\u624d\u6703\u63a5\u53d7\u5230\u4e00\u500b<br />\u771f\u6b63\u7684\u64c1\u62b1", "images": ["http://filestoresg1.beetalkmobile.com:8081/file/b80474312ba65ba0621f3ebdef878c6e"], "urls": [], "title": "\u9084\u8981\u591a\u4e45"}, "threadStatus": 1, "regionId": 886, "barStatus": 0, "barId": 707, "postBy": {"utc": 1498446585000, "level": 9, "location": "\u65b0\u7af9\u5e02\u00b7\u53f0\u7063", "avatar": "http://filestoresg1.beetalkmobile.com:8081/file/-5649661261893833456", "name": "\u3002"}, "id": 6159099}
