{"forum": {"content": "\u9ad8\u96c4\u71b1\u6b7b\u4eba", "images": ["http://filestoresg1.beetalkmobile.com:8081/file/b6dfb46d513c2f33ae1411abd44ad543", "http://filestoresg1.beetalkmobile.com:8081/file/b2ea9f7f9b6f04e897177758b1bb4e77", "http://filestoresg1.beetalkmobile.com:8081/file/37011624a56968f1cd1da39cb186df31", "http://filestoresg1.beetalkmobile.com:8081/file/6ea822208ce08f1cb253ded8e0bfb344", "http://filestoresg1.beetalkmobile.com:8081/file/7e533b478cd39502b8eb686083ff15ca"], "urls": [], "title": "\u71b1\u71b1"}, "threadStatus": 0, "regionId": 886, "barStatus": 0, "barId": 605, "postBy": {"utc": 1498971628000, "level": 2, "location": "\u9ad8\u96c4\u5e02\u00b7\u53f0\u7063", "avatar": "http://filestoresg1.beetalkmobile.com:8081/file/1214794336142478693", "name": "\u308f\u3063\u304b\u306a\u3044"}, "id": 6192677}
