{"forum": {"content": "\u8981\u6c42\u53e6\u4e00\u534a\u8981\u7a7f\u7403\u8863\u53ef\u4ee5\uff01\u4f46\u8981\u7a7f\u5167\u642d\u6709\u932f\u55ce0.0<br />....\u2026", "images": ["http://filestoresg1.beetalkmobile.com:8081/file/e048aae7962fc2b78a5a1d251b7520af"], "urls": [], "title": "\u6c42\u89e3#\u7403\u8863#\u5167\u642d"}, "threadStatus": 1, "regionId": 886, "barStatus": 0, "barId": 18, "postBy": {"utc": 1502284713000, "level": 1, "location": "\u53f0\u4e2d\u5e02\u00b7\u53f0\u7063", "avatar": "http://filestoresg1.beetalkmobile.com:8081/file/-250923944877888000", "name": "Curry"}, "id": 6416519}
