{"forum": {"content": "\u670969\u5e741\u670827\u65e5\u751f\u7684\u55ce\uff1f", "images": ["http://filestoresg1.beetalkmobile.com:8081/file/182b4d7ddf9eea9123c8d54c4ac4e5e0"], "urls": [], "title": "\u670969\u5e741\u670827\u65e5\u751f\u7684\u55ce\uff1f"}, "threadStatus": 0, "regionId": 886, "barStatus": 0, "barId": 765, "postBy": {"utc": 1496536493000, "level": 1, "location": "\u53f0\u4e2d\u5e02\u00b7\u53f0\u7063", "avatar": "http://filestoresg1.beetalkmobile.com:8081/file/4914390382904605193", "name": "\u56de\u61b6\u90a3\u9ebc\u50b7"}, "id": 6033053}
