{"forum": {"content": "\u81ea\u5df1\u52d5\u624b\u505a~<br />\u9178\u751c\u6ab8\u6aac\u916a\u679c\u91ac\uff0c\u62b9\u5410\u53f8\u3001\u86cb\u7cd5\u3001\u9905\u4e7e\u4e0a\uff0c\u9178\u751c\u53ef\u53e3\u3002", "images": ["http://filestoresg1.beetalkmobile.com:8081/file/2cabbe1a3ca920f1d0f659ed6315162c", "http://filestoresg1.beetalkmobile.com:8081/file/2aaefa59aa63eda447c271b8917d12e5", "http://filestoresg1.beetalkmobile.com:8081/file/253c568f2096c0b84951af6b06320a6a", "http://filestoresg1.beetalkmobile.com:8081/file/fec6fe026f36fe12d6df5edb0318885d", "http://filestoresg1.beetalkmobile.com:8081/file/331284c1c00ff24be8d078a245ee3041", "http://filestoresg1.beetalkmobile.com:8081/file/33804612bb9dd282f3dd9b91022f8895"], "urls": [], "title": "\u590f\u5929\u4f86\u500b\u9178\u9178\u751c\u751c\u7684\u6ab8\u6aac\u916a\u91ac~"}, "threadStatus": 0, "regionId": 886, "barStatus": 0, "barId": 98, "postBy": {"utc": 1497762346000, "level": 0, "location": "\u65b0\u5317\u5e02\u00b7\u53f0\u7063", "avatar": "http://filestoresg1.beetalkmobile.com:8081/file/-6277598960855162402", "name": "\u2744\ud83c\udf38Anita\ud83c\udf38\u2744 "}, "id": 6115476}
