{"forum": {"content": "\u4e00\u8d77\u4f86talk\u4e00\u4e0b<br /><br />\u4f86\u8a8d\u8b58\u4e00\u4e0b\u5427<br /><br />IG more54120", "images": ["http://filestoresg1.beetalkmobile.com:8081/file/59b342acdd738db26726ec8897807c8b"], "urls": [], "title": "\u55ae\u8eabT"}, "threadStatus": 0, "regionId": 886, "barStatus": 0, "barId": 20, "postBy": {"utc": 1504097115000, "level": 3, "location": "\u9ad8\u96c4\u5e02\u00b7\u53f0\u7063", "avatar": "http://filestoresg1.beetalkmobile.com:8081/file/-1923669236716669435", "name": "Mo"}, "id": 6542027}
