{"forum": {"content": "\u9ad4\u80fd\u6e2c\u9a57\u98b1\u98a8\u5ef6\u671f  \u5165\u4f0d\u4e5f\u98b1\u98a8\u5ef6\u671f \u7b2c\u4e94\u68af\u771f\u7684\u8ddf\u98b1\u98a8\u904e\u4e0d\u53bb \ud83d\ude21<br /><br />\u81ea\u5df1\u9084\u8981\u5ef6\u9577\u53bb\u62bd\u7c64\u4e86", "images": ["http://filestoresg1.beetalkmobile.com:8081/file/395454d4a13e98cd975eb0250494d070"], "urls": [], "title": "\u5ef6\u671f"}, "threadStatus": 0, "regionId": 886, "barStatus": 0, "barId": 704, "postBy": {"utc": 1505188977000, "level": 15, "location": "Kaohsiung City\u00b7Taiwan", "avatar": "http://filestoresg1.beetalkmobile.com:8081/file/4721011561713718274", "name": "hank"}, "id": 6614960}
