{"forum": {"content": "\u53ef\u8a0e\u8ad6\u4e3b\u984c\u53ca\u63d0\u4f9b\u8863\u670d", "images": ["http://filestoresg1.beetalkmobile.com:8081/file/aed10dfcd5cd4c3599b8fcd5d6bb1e23", "http://filestoresg1.beetalkmobile.com:8081/file/10fb0dcf128c534048483ba3d02a6446", "http://filestoresg1.beetalkmobile.com:8081/file/89fc1a526168f3ffa5362d6f8fe5ddcf", "http://filestoresg1.beetalkmobile.com:8081/file/9c2fdca2db25368687277a1f9fe4b1ba", "http://filestoresg1.beetalkmobile.com:8081/file/0b7e318bb2ffeb23cc8a46f38e588e87", "http://filestoresg1.beetalkmobile.com:8081/file/e8668629b848f8272592688545addaf5"], "urls": [], "title": "\u6b61\u8fce\u9810\u7d04\u62cd\u4f5c\u54c1\u5206\u4eab"}, "threadStatus": 1, "regionId": 886, "barStatus": 0, "barId": 77, "postBy": {"utc": 1502275336000, "level": 10, "location": "\u53f0\u4e2d\u5e02\u00b7\u53f0\u7063", "avatar": "http://filestoresg1.beetalkmobile.com:8081/file/-6336984665945721344", "name": "\u9ec3\u6fdf\u5b87"}, "id": 6415746}
