{"forum": {"content": "\u6709\u54ea\u500b\u5973\u751f\u9858\u610f\u660e\u5929\u966a\u6211\u53bb\u6c7a\u6c5f\u901b\u8857", "images": ["http://filestoresg1.beetalkmobile.com:8081/file/7e2f0048aa25697c3d2ad80d8d09d688"], "urls": [], "title": "\u9650\u5973\u751f"}, "threadStatus": 1, "regionId": 886, "barStatus": 0, "barId": 676, "postBy": {"utc": 1497635293000, "level": 8, "location": "\u9ad8\u96c4\u5e02\u00b7\u53f0\u7063", "avatar": "http://filestoresg1.beetalkmobile.com:8081/file/-1464339480533739331", "name": "^^"}, "id": 6107808}
