{"forum": {"content": "\u9019\u88e1\u53ef\u6c92\u6709\u5e25\u54e5\uff01\u55ae\u7d14\u8cbc\u6587\u8a66\u73a9\uff01\u4e0d\u597d\u610f\u601d\u50b7\u4f60\u5011\u773c\u775b", "images": ["http://filestoresg1.beetalkmobile.com:8081/file/a336896c88ea3ad1168b9691e60a1e94", "http://filestoresg1.beetalkmobile.com:8081/file/fbb1547304c75bac517500a5462fcea0", "http://filestoresg1.beetalkmobile.com:8081/file/f25dfaef63c8e57fd2e277252b3f788b", "http://filestoresg1.beetalkmobile.com:8081/file/add377a5d062c3a0f5bcbb05fa4251b4"], "urls": [], "title": "\u6253\u816b\u81c9\u6490\u5e25\u54e5"}, "threadStatus": 1, "regionId": 886, "barStatus": 0, "barId": 33, "postBy": {"utc": 1496271649000, "level": 0, "location": "\u65b0\u5317\u5e02\u00b7\u53f0\u7063", "avatar": "http://filestoresg1.beetalkmobile.com:8081/file/2284033112383800834", "name": "Ziv Chen"}, "id": 6015491}
