{"forum": {"content": "ooo", "images": ["http://filestoresg1.beetalkmobile.com:8081/file/495988075c1ddbf6cbc81488ae1a8cd6", "http://filestoresg1.beetalkmobile.com:8081/file/f98f4f1c3e1f80582c7c2eb14e47b923", "http://filestoresg1.beetalkmobile.com:8081/file/b61728489c704dd7f5ae9292be9ef45d"], "urls": [], "title": "ooo"}, "threadStatus": 1, "regionId": 886, "barStatus": 0, "barId": 4, "postBy": {"utc": 1500217997000, "level": 2, "location": "\u65b0\u7af9\u5e02\u00b7\u53f0\u7063", "avatar": "http://filestoresg1.beetalkmobile.com:8081/file/6350321766890004204", "name": "\u65e9"}, "id": 6276518}
