{"forum": {"content": "\u5f88\u591a\u4eba\u8ffd\u59b3\u7684\u8a71\u5343\u842c\u5225\u5f97\u610f<br />\u5c31\u50cf\u8db3\u7403\u5834\u4e0a22\u500b\u4eba\u8ffd\u4e00\u9846\u7403<br />\u4ed6\u5011\u4e0d\u662f\u70ba\u4e86\u5f97\u5230<br />\u800c\u662f\u53ea\u60f3\u5c04\u9032\u53bb", "images": ["http://filestoresg1.beetalkmobile.com:8081/file/7cc227ec7894aeb336ae4f67f8704e05"], "urls": [], "title": "\u662f\u55ce\uff1f"}, "threadStatus": 0, "regionId": 886, "barStatus": 0, "barId": 205, "postBy": {"utc": 1501074158000, "level": 3, "location": "\u65b0\u5317\u5e02\u00b7\u53f0\u7063", "avatar": "http://filestoresg1.beetalkmobile.com:8081/file/8277181830964402699", "name": "\u7259\u5957\u59ca\ud83c\udf88"}, "id": 6334608}
