{"forum": {"content": "\u9b5a\u4e38\u9644\u8fd1", "images": ["http://filestoresg1.beetalkmobile.com:8081/file/01d0c1799ef0a45c0505ea6a3425ffc5", "http://filestoresg1.beetalkmobile.com:8081/file/078d7c70830496ebc25fde7aec199ec8", "http://filestoresg1.beetalkmobile.com:8081/file/b66340b9600ac81caf9cecf624d1ef79", "http://filestoresg1.beetalkmobile.com:8081/file/09b193b2ae8536dde69bc06a7c019044", "http://filestoresg1.beetalkmobile.com:8081/file/4e426edb97d0e54a8d8ee756855ba0fe", "http://filestoresg1.beetalkmobile.com:8081/file/9d5c6cf1631ea9c7da7f6b83a46f7fd5"], "urls": [], "title": "\u5927\u767d\u9bca"}, "threadStatus": 0, "regionId": 886, "barStatus": 0, "barId": 77, "postBy": {"utc": 1509521936000, "level": 6, "location": "", "avatar": "http://filestoresg1.beetalkmobile.com:8081/file/-2103488875559623936", "name": "\u653e\u8005\u81ed \ud83d\ude40"}, "id": 6937765}
