{"forum": {"content": "\u4e00\u500b\u5c0f\u968a\uff01", "images": ["http://filestoresg1.beetalkmobile.com:8081/file/3b9fad9432ba981810567b5d0ce25ac8", "http://filestoresg1.beetalkmobile.com:8081/file/ca6d50a0e7d2f575a846bdf6001bbe0a", "http://filestoresg1.beetalkmobile.com:8081/file/98e699b791f8fa6f64cb6f10bb88c944", "http://filestoresg1.beetalkmobile.com:8081/file/36d0b26aece30ae316f7fab6446bf1f7", "http://filestoresg1.beetalkmobile.com:8081/file/ed6b5d6526ebafad880c87f1cdf09963", "http://filestoresg1.beetalkmobile.com:8081/file/0fe148b1d897b2d19b0d57c39ecf01fc"], "urls": [], "title": "UN\u76d2\u73a9"}, "threadStatus": 0, "regionId": 886, "barStatus": 0, "barId": 207, "postBy": {"utc": 1504703069000, "level": 3, "location": "\u65b0\u754c\u00b7\u9999\u6e2f", "avatar": "http://filestoresg1.beetalkmobile.com:8081/file/8369915734013300441", "name": "HK\u80a5"}, "id": 6582426}
