{"forum": {"content": "\u5982\u679c\u6211\u8aaa\u6211\u662f\u570b\u4e09\u751f\u4f60\u76f8\u4fe1\u561b\ud83d\ude05", "images": ["http://filestoresg1.beetalkmobile.com:8081/file/40486f00fabc6181aa004d819a76650e"], "urls": [], "title": "\u5982\u679c\u6211\u8aaa\u6211\u662f..."}, "threadStatus": 0, "regionId": 886, "barStatus": 0, "barId": 4, "postBy": {"utc": 1503399684000, "level": 2, "location": "\u65b0\u5317\u5e02\u00b7\u53f0\u7063", "avatar": "http://filestoresg1.beetalkmobile.com:8081/file/8338424628065209402", "name": "\u9ede\u958b\u624d\u770b\u5f97\u5230\u6211"}, "id": 6493534}
