{"forum": {"content": "\u52a0\u4e86\u53c8\u4e0d\u56de\u2026<br />\u8b1d\u8b1d \u8981\u9019\u6a23\u81ea\u522a<br />\u5e7d\u9748\u4eba\u53e3\u6211\u4e0d\u7f3a", "images": ["http://filestoresg1.beetalkmobile.com:8081/file/e46834c5222cbd06e125a0dee37fe7df"], "urls": [], "title": "\u8ddf\u963f\u80a5\u505a\u670b\u53cb"}, "threadStatus": 0, "regionId": 886, "barStatus": 0, "barId": 205, "postBy": {"utc": 1499328893000, "level": 2, "location": "\u81fa\u4e2d\u5e02\u00b7\u53f0\u7063", "avatar": "http://filestoresg1.beetalkmobile.com:8081/file/-9119848596151528766", "name": "\u591a\u591a"}, "id": 6215883}
