{"forum": {"content": "\u6709\u5fc3\u8981\u804a\u8981\u8a8d\u8b58\u518d\u4f86\u52a0\u597d\u53cb<br />\u5225\u6211\u78ba\u8a8d\u4e86\u4e4b\u5f8c\u53c8\u4e0d\u804a<br />\u6709\u4eba\u9858\u610f\u8ddf140\u804a\u804a\u5929\u561b\ud83d\ude02<br />\u6709T\u8981\u4f86\u8a8d\u8b58\u804a\u804a\u561b\ud83d\ude4c<br /><br />\u7136\u5f8c\u7136\u5f8c<br />\u6709Ig\u7684\u4e5f\u4e00\u8d77\u4e92\u8ffd\u4e00\u4e0b \u6211\u6bd4\u8f03\u5e38\u7528Ig\u767c\u6587\ud83d\ude0e<br />By the way<br />\u5343\u842c\u5343\u842c\u5225\u5e7d\u9748 \u8b1d\u8b1d\u914d\u5408\ud83d\ude46<br />", "images": ["http://filestoresg1.beetalkmobile.com:8081/file/68cd6ed85bbe99d21aa5d2c8912f7dca", "http://filestoresg1.beetalkmobile.com:8081/file/028130552907c91d8787e9205079a783"], "urls": [], "title": "\u6a19\u984c\u4e0d\u91cd\u8981 \u5167\u5bb9\u624d\u91cd\u8981\ud83d\ude02\ud83d\ude02"}, "threadStatus": 1, "regionId": 886, "barStatus": 0, "barId": 20, "postBy": {"utc": 1508520311000, "level": 24, "location": "\u9ad8\u96c4\u5e02\u00b7\u53f0\u7063", "avatar": "http://filestoresg1.beetalkmobile.com:8081/file/2244620006201072535", "name": "\u77ee\u5b50\ud83d\ude4c"}, "id": 6869429}
