{"forum": {"content": "\u4e00\u7728\u773c\uff0c\u5f77\u5f7f\u4e00\u7728\u773c\uff0c\u5c3138\u6b72\u4e86\uff0c\u4e0d\u5f97\u4e0d\u63a5\u53d7\u5fae\u5410\u7684\u5c0f\u8179\uff0c\u65b0\u9673\u4ee3\u8b1d\u8b8a\u6162\u7684\u7a98\u5883", "images": ["http://filestoresg1.beetalkmobile.com:8081/file/25ff464b3f79cf4f7e324b6848fa46f8", "http://filestoresg1.beetalkmobile.com:8081/file/82d0a16405ad1c1c67e089abe8a2f53d"], "urls": [], "title": "38\u4e86\u2026\u2026"}, "threadStatus": 0, "regionId": 886, "barStatus": 0, "barId": 838, "postBy": {"utc": 1502594455000, "level": 3, "location": "\u65b0\u5317\u5e02\u00b7\u53f0\u7063", "avatar": "http://filestoresg1.beetalkmobile.com:8081/file/5475569020872443393", "name": "\u8001\u9673"}, "id": 6436612}
